thunderbeard/__init__.py
thunderbeard/modules.py
thunderbeard-0.1.0.dist-info/LICENSE
thunderbeard-0.1.0.dist-info/METADATA
thunderbeard-0.1.0.dist-info/WHEEL
thunderbeard-0.1.0.dist-info/top_level.txt
thunderbeard-0.1.0.dist-info/RECORD
