Metadata-Version: 2.1
Name: thunderbeard
Version: 0.1.0
Summary: Minimal python deep learning library
Author: Ax-Time
License: MIT
License-File: LICENSE
Requires-Dist: jax
Requires-Dist: jaxlib
Requires-Dist: numpy
